sqlbot_xpack/__init__.py
sqlbot_xpack/aes_utils.cpython-311-darwin.so
sqlbot_xpack/core.cpython-311-darwin.so
sqlbot_xpack/db.cpython-311-darwin.so
sqlbot_xpack/file_utils.cpython-311-darwin.so
sqlbot_xpack/url_utils.cpython-311-darwin.so
sqlbot_xpack/authentication/__init__.py
sqlbot_xpack/authentication/api.cpython-311-darwin.so
sqlbot_xpack/authentication/cas_client.cpython-311-darwin.so
sqlbot_xpack/authentication/ldap_client.cpython-311-darwin.so
sqlbot_xpack/authentication/manage.cpython-311-darwin.so
sqlbot_xpack/authentication/mapping_utils.cpython-311-darwin.so
sqlbot_xpack/authentication/oauth2_client.cpython-311-darwin.so
sqlbot_xpack/authentication/oidc_client.cpython-311-darwin.so
sqlbot_xpack/authentication/schemas.cpython-311-darwin.so
sqlbot_xpack/authentication/utils.cpython-311-darwin.so
sqlbot_xpack/config/__init__.py
sqlbot_xpack/config/api.cpython-311-darwin.so
sqlbot_xpack/config/arg_api.cpython-311-darwin.so
sqlbot_xpack/config/arg_manage.cpython-311-darwin.so
sqlbot_xpack/config/model.cpython-311-darwin.so
sqlbot_xpack/config/rsa_manage.cpython-311-darwin.so
sqlbot_xpack/custom_prompt/__init__.py
sqlbot_xpack/custom_prompt/api/__init__.py
sqlbot_xpack/custom_prompt/api/custom_prompt.cpython-311-darwin.so
sqlbot_xpack/custom_prompt/curd/__init__.py
sqlbot_xpack/custom_prompt/curd/custom_prompt.cpython-311-darwin.so
sqlbot_xpack/custom_prompt/models/__init__.py
sqlbot_xpack/custom_prompt/models/custom_prompt_model.cpython-311-darwin.so
sqlbot_xpack/embedded/__init__.py
sqlbot_xpack/embedded/api.cpython-311-darwin.so
sqlbot_xpack/factory/__init__.py
sqlbot_xpack/factory/generic_factory.cpython-311-darwin.so
sqlbot_xpack/license/__init__.py
sqlbot_xpack/license/api.cpython-311-darwin.so
sqlbot_xpack/license/license_manage.cpython-311-darwin.so
sqlbot_xpack/license/model.cpython-311-darwin.so
sqlbot_xpack/license/schema.cpython-311-darwin.so
sqlbot_xpack/license/xpack_handler.cpython-311-darwin.so
sqlbot_xpack-0.0.3.59.dist-info/METADATA
sqlbot_xpack-0.0.3.59.dist-info/WHEEL
sqlbot_xpack-0.0.3.59.dist-info/top_level.txt
sqlbot_xpack-0.0.3.59.dist-info/RECORD
