Metadata-Version: 2.4
Name: sqlbot-xpack
Version: 0.0.3.59
Summary: SQL Bot SDK
Author-email: fit2cloud-chenyw <yawen.chen@fit2cloud.com>
Requires-Python: <3.13,>=3.10
Requires-Dist: cython>=3.1.2
Requires-Dist: fastapi[standard]<1.0.0,>=0.115.12
Requires-Dist: sqlmodel<1.0.0,>=0.0.21
Requires-Dist: pycryptodome>=3.23.0
Requires-Dist: setuptools>=80.9.0
